plugapi/__init__.py
plugapi/http.py
plugapi-1.2.3.dist-info/licenses/LICENSE
plugapi-1.2.3.dist-info/METADATA
plugapi-1.2.3.dist-info/WHEEL
plugapi-1.2.3.dist-info/top_level.txt
plugapi-1.2.3.dist-info/RECORD
