Metadata-Version: 2.4
Name: plugapi
Version: 1.2.3
Summary: A lightweight, speedy HTTP(S) server
Author-email: Aarav Malani <aarav.malani@gmail.com>
Project-URL: Homepage, https://github.com/AaravMalani/PlugAPI
Project-URL: Bug Tracker, https://github.com/AaravMalani/PlugAPI/issues
Classifier: Programming Language :: Python :: 3
Classifier: License :: OSI Approved :: MIT License
Classifier: Operating System :: OS Independent
Requires-Python: >=3.6
License-File: LICENSE
Dynamic: license-file
